{
 "regime": "neutral",
 "generated_at": "2026-07-08T16:04:02",
 "gainers": [
  {
   "id": "SCHD",
   "name": "Schwab 高股息",
   "price": 32.46,
   "chg": 0.67,
   "vr": 1.0,
   "value": 2.9
  },
  {
   "id": "VYM",
   "name": "Vanguard 高股息",
   "price": 159.97,
   "chg": -0.11,
   "vr": 1.1,
   "value": 1.1
  },
  {
   "id": "VOO",
   "name": "Vanguard S&P 500",
   "price": 681.16,
   "chg": -1.37,
   "vr": 0.5,
   "value": 17.7
  },
  {
   "id": "TLT",
   "name": "iShares 20年美債",
   "price": 84.15,
   "chg": -1.52,
   "vr": 0.9,
   "value": 7.7
  },
  {
   "id": "VTI",
   "name": "Vanguard 全美股",
   "price": 366.0,
   "chg": -1.53,
   "vr": 1.1,
   "value": 5.8
  }
 ],
 "losers": [
  {
   "id": "TQQQ",
   "name": "ProShares Nasdaq 正3",
   "price": 70.25,
   "chg": -8.07,
   "vr": 1.4,
   "value": 30.6
  },
  {
   "id": "SMH",
   "name": "VanEck 半導體",
   "price": 580.66,
   "chg": -3.91,
   "vr": 0.9,
   "value": 26.1
  },
  {
   "id": "QQQ",
   "name": "Invesco Nasdaq 100",
   "price": 703.19,
   "chg": -2.72,
   "vr": 0.9,
   "value": 128.3
  },
  {
   "id": "VT",
   "name": "Vanguard 全世界",
   "price": 154.65,
   "chg": -2.01,
   "vr": 0.5,
   "value": 1.3
  },
  {
   "id": "VTI",
   "name": "Vanguard 全美股",
   "price": 366.0,
   "chg": -1.53,
   "vr": 1.1,
   "value": 5.8
  }
 ],
 "volume": [
  {
   "id": "TQQQ",
   "name": "ProShares Nasdaq 正3",
   "price": 70.25,
   "chg": -8.07,
   "vr": 1.4,
   "value": 30.6
  },
  {
   "id": "VTI",
   "name": "Vanguard 全美股",
   "price": 366.0,
   "chg": -1.53,
   "vr": 1.1,
   "value": 5.8
  },
  {
   "id": "VYM",
   "name": "Vanguard 高股息",
   "price": 159.97,
   "chg": -0.11,
   "vr": 1.1,
   "value": 1.1
  },
  {
   "id": "SCHD",
   "name": "Schwab 高股息",
   "price": 32.46,
   "chg": 0.67,
   "vr": 1.0,
   "value": 2.9
  },
  {
   "id": "QQQ",
   "name": "Invesco Nasdaq 100",
   "price": 703.19,
   "chg": -2.72,
   "vr": 0.9,
   "value": 128.3
  }
 ],
 "industries": [],
 "weak_industries": []
}