{
 "regime": "neutral",
 "generated_at": "2026-07-16T06:40:39",
 "gainers": [
  {
   "id": "6243",
   "name": "迅杰",
   "price": 47.95,
   "chg": 33.01,
   "vr": 2.9,
   "value": 2.0
  },
  {
   "id": "6505",
   "name": "台塑化",
   "price": 80.0,
   "chg": 26.78,
   "vr": 8.3,
   "value": 80.8
  },
  {
   "id": "6949",
   "name": "沛爾生醫-創",
   "price": 1105.0,
   "chg": 22.78,
   "vr": 2.8,
   "value": 8.7
  },
  {
   "id": "2466",
   "name": "冠西電",
   "price": 121.0,
   "chg": 20.4,
   "vr": 0.8,
   "value": 2.0
  },
  {
   "id": "8039",
   "name": "台虹",
   "price": 199.5,
   "chg": 18.05,
   "vr": 1.6,
   "value": 27.9
  }
 ],
 "losers": [
  {
   "id": "2483",
   "name": "百容",
   "price": 48.3,
   "chg": -21.08,
   "vr": 0.6,
   "value": 2.3
  },
  {
   "id": "3090",
   "name": "日電貿",
   "price": 209.0,
   "chg": -18.99,
   "vr": 0.9,
   "value": 22.7
  },
  {
   "id": "2492",
   "name": "華新科",
   "price": 341.5,
   "chg": -18.5,
   "vr": 0.4,
   "value": 15.9
  },
  {
   "id": "6834",
   "name": "天二科技",
   "price": 107.0,
   "chg": -17.05,
   "vr": 0.7,
   "value": 4.4
  },
  {
   "id": "3026",
   "name": "禾伸堂",
   "price": 766.0,
   "chg": -15.36,
   "vr": 2.0,
   "value": 112.5
  }
 ],
 "volume": [
  {
   "id": "5306",
   "name": "桂盟",
   "price": 99.2,
   "chg": 11.71,
   "vr": 11.2,
   "value": 1.8
  },
  {
   "id": "6533",
   "name": "晶心科",
   "price": 228.0,
   "chg": 8.31,
   "vr": 9.0,
   "value": 7.8
  },
  {
   "id": "6505",
   "name": "台塑化",
   "price": 80.0,
   "chg": 26.78,
   "vr": 8.3,
   "value": 80.8
  },
  {
   "id": "3033",
   "name": "威健",
   "price": 54.2,
   "chg": 6.48,
   "vr": 8.2,
   "value": 33.0
  },
  {
   "id": "9914",
   "name": "美利達",
   "price": 84.2,
   "chg": 11.67,
   "vr": 5.8,
   "value": 10.9
  }
 ],
 "industries": [
  {
   "name": "油電燃氣業",
   "value": 83.26,
   "chg": 25.91
  },
  {
   "name": "創新版股票",
   "value": 9.7,
   "chg": 20.31
  },
  {
   "name": "塑膠工業",
   "value": 465.95,
   "chg": 9.4
  }
 ],
 "weak_industries": [
  {
   "name": "觀光事業",
   "value": 4.8,
   "chg": -6.61
  },
  {
   "name": "運動休閒",
   "value": 0.87,
   "chg": -3.49
  },
  {
   "name": "光電業",
   "value": 421.98,
   "chg": -3.08
  }
 ]
}